pretix_payone/__init__.py
pretix_payone/apps.py
pretix_payone/models.py
pretix_payone/payment.py
pretix_payone/signals.py
pretix_payone/urls.py
pretix_payone/views.py
pretix_payone/locale/django.pot
pretix_payone/locale/djangojs.pot
pretix_payone/locale/de/LC_MESSAGES/django.mo
pretix_payone/locale/de/LC_MESSAGES/django.po
pretix_payone/locale/de/LC_MESSAGES/djangojs.mo
pretix_payone/locale/de/LC_MESSAGES/djangojs.po
pretix_payone/locale/de_Informal/.gitkeep
pretix_payone/locale/de_Informal/LC_MESSAGES/django.mo
pretix_payone/locale/de_Informal/LC_MESSAGES/django.po
pretix_payone/locale/de_Informal/LC_MESSAGES/djangojs.mo
pretix_payone/locale/de_Informal/LC_MESSAGES/djangojs.po
pretix_payone/migrations/0001_initial.py
pretix_payone/migrations/0002_auto_20220204_1638.py
pretix_payone/migrations/__init__.py
pretix_payone/static/pretix_payone/.gitkeep
pretix_payone/static/pretix_payone/cc.js
pretix_payone/static/pretix_payone/logo.svg
pretix_payone/templates/pretix_payone/.gitkeep
pretix_payone/templates/pretix_payone/checkout_payment_confirm.html
pretix_payone/templates/pretix_payone/checkout_payment_form.html
pretix_payone/templates/pretix_payone/checkout_payment_form_cc.html
pretix_payone/templates/pretix_payone/control.html
pretix_payone/templates/pretix_payone/pending.html
pretix_payone/templates/pretix_payone/redirect.html
pretix_payone-1.4.1.dist-info/licenses/LICENSE
pretix_payone-1.4.1.dist-info/METADATA
pretix_payone-1.4.1.dist-info/WHEEL
pretix_payone-1.4.1.dist-info/entry_points.txt
pretix_payone-1.4.1.dist-info/top_level.txt
pretix_payone-1.4.1.dist-info/RECORD
