Metadata-Version: 2.4
Name: pretix-payone
Version: 1.4.1
Summary: Allows to process payments through PAYONE (formerly BS Payone)
Author-email: pretix team <support@pretix.eu>
Maintainer-email: pretix team <support@pretix.eu>
License: 
Project-URL: homepage, https://github.com/pretix/pretix-payone
Keywords: pretix
Requires-Python: >=3.9
License-File: LICENSE
Dynamic: license-file
